{
  "primary": {
    "path": "debug\\solver_io\\20260519\\hand_000006_req_000007_flop.json",
    "success": false,
    "elapsed_ms": 30606,
    "action": null,
    "amount": null,
    "probabilities": {},
    "error": "Solver timeout (no response within 30.0s)"
  },
  "compare": {
    "path": "debug\\solver_io\\20260519\\hand_000006_req_000008_flop_compare_no_allin.json",
    "success": true,
    "elapsed_ms": 29340,
    "action": "BET",
    "amount": 139,
    "probabilities": {
      "Check": 0.2670510570821678,
      "Bet 139": 0.7329489444924078
    },
    "error": null
  },
  "light": {
    "path": "generated_light_probe_from:debug\\solver_io\\20260519\\hand_000006_req_000007_flop.json",
    "success": true,
    "elapsed_ms": 16448,
    "action": "BET",
    "amount": 116,
    "probabilities": {
      "Check": 0.3957732013615011,
      "Bet 116": 0.6042267725614668
    },
    "error": null
  },
  "middle": {
    "path": "generated_middle_probe_from:debug\\solver_io\\20260519\\hand_000006_req_000007_flop.json",
    "success": true,
    "elapsed_ms": 18462,
    "action": "BET",
    "amount": 139,
    "probabilities": {
      "Check": 0.1061487397061544,
      "Bet 139": 0.8938512638229139
    },
    "error": null
  },
  "fast_middle": {
    "path": "generated_fast_middle_probe_from:debug\\solver_io\\20260519\\hand_000006_req_000007_flop.json",
    "success": true,
    "elapsed_ms": 22937,
    "action": "BET",
    "amount": 139,
    "probabilities": {
      "Check": 0.1485879162465732,
      "Bet 139": 0.8514120911915889
    },
    "error": null
  },
  "summary": {
    "compare_action_match": false,
    "compare_amount_match": false,
    "compare_speedup_ratio": 1.043,
    "light_action_match": false,
    "light_amount_match": false,
    "light_speedup_ratio": 1.861,
    "middle_action_match": false,
    "middle_amount_match": false,
    "middle_speedup_ratio": 1.658,
    "fast_middle_action_match": false,
    "fast_middle_amount_match": false,
    "fast_middle_speedup_ratio": 1.334,
    "fast_middle_under_15s": false
  }
}